mocca/__init__.py
mocca/py.typed
mocca/campaign/__init__.py
mocca/campaign/experiment_funcs.py
mocca/campaign/process_funcs.py
mocca/campaign/utils.py
mocca/campaign/.ipynb_checkpoints/experiment_funcs-checkpoint.py
mocca/chromatogram/__init__.py
mocca/chromatogram/assign.py
mocca/chromatogram/correct.py
mocca/chromatogram/model.py
mocca/chromatogram/preprocessor.py
mocca/chromatogram/quantify.py
mocca/chromatogram/utils.py
mocca/chromatogram/.ipynb_checkpoints/correct-checkpoint.py
mocca/chromatogram/.ipynb_checkpoints/preprocessor-checkpoint.py
mocca/chromatogram/.ipynb_checkpoints/utils-checkpoint.py
mocca/components/__init__.py
mocca/components/databases.py
mocca/components/models.py
mocca/components/quali_funcs.py
mocca/components/quant_funcs.py
mocca/components/utils.py
mocca/components/.ipynb_checkpoints/__init__-checkpoint.py
mocca/components/.ipynb_checkpoints/databases-checkpoint.py
mocca/components/.ipynb_checkpoints/models-checkpoint.py
mocca/components/.ipynb_checkpoints/quali_funcs-checkpoint.py
mocca/components/.ipynb_checkpoints/quant_funcs-checkpoint.py
mocca/components/.ipynb_checkpoints/utils-checkpoint.py
mocca/dad_data/__init__.py
mocca/dad_data/models.py
mocca/dad_data/process_funcs.py
mocca/dad_data/process_gradientdata.py
mocca/dad_data/utils.py
mocca/dad_data/.ipynb_checkpoints/__init__-checkpoint.py
mocca/dad_data/.ipynb_checkpoints/models-checkpoint.py
mocca/dad_data/.ipynb_checkpoints/process_funcs-checkpoint.py
mocca/dad_data/.ipynb_checkpoints/process_gradientdata-checkpoint.py
mocca/dad_data/.ipynb_checkpoints/utils-checkpoint.py
mocca/dad_data/apis/__init__.py
mocca/dad_data/apis/allotrope.py
mocca/dad_data/apis/angi.py
mocca/dad_data/apis/chemstation.py
mocca/dad_data/apis/custom.py
mocca/dad_data/apis/empower.py
mocca/dad_data/apis/labsolutions.py
mocca/dad_data/apis/.ipynb_checkpoints/allotrope-checkpoint.py
mocca/dad_data/apis/.ipynb_checkpoints/empower-checkpoint.py
mocca/decomposition/alternative_objective_funcs.py
mocca-0.1.5.dist-info/LICENSE.txt
mocca-0.1.5.dist-info/METADATA
mocca-0.1.5.dist-info/WHEEL
mocca-0.1.5.dist-info/top_level.txt
mocca-0.1.5.dist-info/RECORD
