Metadata-Version: 2.1
Name: mocca
Version: 0.1.5
Summary: MOCCA (Multivariate Online Contextual Chromatographic Analysis) is an open-source Python project to analyze HPLC–DAD raw data.
Home-page: https://github.com/HaasCP/mocca
Author: HaasCP
Author-email: 57134208+HaasCP@users.noreply.github.com
License: MIT
Project-URL: Documentation, https://mocca.readthedocs.io/en/latest/readme.html
Platform: any
Classifier: Development Status :: 4 - Beta
Classifier: Programming Language :: Python
Requires-Python: >=3.6
License-File: LICENSE.txt
Requires-Dist: numpy<2.0.0,>=1.21.2
Requires-Dist: pandas<2.0.0,>=1.3.4
Requires-Dist: scipy<2.0.0,>=1.7.2
Requires-Dist: matplotlib<4.0.0,>=3.4.3
Requires-Dist: scikit-learn<2.0.0,>=0.0.0
Requires-Dist: altair<5.0.0,>=4.1.0
Requires-Dist: tensorly<1.0.0,>=0.7.0
Requires-Dist: dill<1.0.0,>=0.3.4
Requires-Dist: importlib-metadata; python_version < "3.8"
Provides-Extra: testing
Requires-Dist: setuptools; extra == "testing"
Requires-Dist: pytest; extra == "testing"
Requires-Dist: pytest-cov; extra == "testing"
Requires-Dist: flake8; extra == "testing"
Requires-Dist: mypy; extra == "testing"
